DeepLScrapper/__init__.py
DeepLScrapper/translator.py
DeepLScrapper/webapp.py
DeepLScrapper-1.8.0.dist-info/LICENSE
DeepLScrapper-1.8.0.dist-info/METADATA
DeepLScrapper-1.8.0.dist-info/WHEEL
DeepLScrapper-1.8.0.dist-info/top_level.txt
DeepLScrapper-1.8.0.dist-info/RECORD
