Metadata-Version: 2.1
Name: DeepLScrapper
Version: 1.8.0
Summary: An unofficial Python library for translating text using DeepL
Home-page: https://github.com/ochotzas/
Author: Olger Chotza
Author-email: olgerdev@icloud.com
License: MIT
Classifier: License :: OSI Approved :: MIT License
Classifier: Programming Language :: Python :: 3
Classifier: Programming Language :: Python :: 3.9
Classifier: Programming Language :: Python :: 3.10
Classifier: Programming Language :: Python :: 3.11
Classifier: Operating System :: OS Independent
Requires-Python: >=3.9
License-File: LICENSE
Requires-Dist: selenium
Requires-Dist: beautifulsoup4
Requires-Dist: fake-useragent
Requires-Dist: sqlite3
Requires-Dist: flask
